SoftwareFoundations/README.md
SoftwareFoundations/__init__.py
SoftwareFoundations/__main__.py
SoftwareFoundations/file.epub
SoftwareFoundations/index.html
SoftwareFoundations/css/__init__.py
SoftwareFoundations/css/annotations.css
SoftwareFoundations/css/main.css
SoftwareFoundations/css/normalize.css
SoftwareFoundations/css/popup.css
SoftwareFoundations/font/__init__.py
SoftwareFoundations/font/fontello.eot
SoftwareFoundations/font/fontello.svg
SoftwareFoundations/font/fontello.ttf
SoftwareFoundations/font/fontello.woff
SoftwareFoundations/img/__init__.py
SoftwareFoundations/img/annotator-glyph-sprite.png
SoftwareFoundations/img/annotator-icon-sprite.png
SoftwareFoundations/img/apple-touch-icon.png
SoftwareFoundations/img/cancelfullscreen.png
SoftwareFoundations/img/close.png
SoftwareFoundations/img/fullscreen.png
SoftwareFoundations/img/loader.gif
SoftwareFoundations/img/menu-icon.png
SoftwareFoundations/img/save.png
SoftwareFoundations/img/saved.png
SoftwareFoundations/img/settings-s.png
SoftwareFoundations/img/settings.png
SoftwareFoundations/img/star.png
SoftwareFoundations/js/__init__.py
SoftwareFoundations/js/epub.js
SoftwareFoundations/js/epub.min.js
SoftwareFoundations/js/epub.min.map
SoftwareFoundations/js/hooks.min.js
SoftwareFoundations/js/hooks.min.map
SoftwareFoundations/js/reader.js
SoftwareFoundations/js/reader.js.map
SoftwareFoundations/js/reader.min.js
SoftwareFoundations/js/reader.min.map
SoftwareFoundations/js/hooks/__init__.py
SoftwareFoundations/js/hooks/extensions/__init__.py
SoftwareFoundations/js/hooks/extensions/highlight.js
SoftwareFoundations/js/libs/__init__.py
SoftwareFoundations/js/libs/jquery.min.js
SoftwareFoundations/js/libs/localforage.min.js
SoftwareFoundations/js/libs/screenfull.js
SoftwareFoundations/js/libs/screenfull.min.js
SoftwareFoundations/js/libs/zip.min.js
SoftwareFoundations/js/plugins/__init__.py
SoftwareFoundations/js/plugins/hypothesis.js
SoftwareFoundations/js/plugins/search.js
software_foundations-2024.3.2.0.dist-info/METADATA
software_foundations-2024.3.2.0.dist-info/WHEEL
software_foundations-2024.3.2.0.dist-info/entry_points.txt
software_foundations-2024.3.2.0.dist-info/top_level.txt
software_foundations-2024.3.2.0.dist-info/RECORD
